README.md
_types.py
flake8_vcs_ext.py
pyproject.toml
flake8_vcs_ext-2.0.2.dist-info/LICENSE
flake8_vcs_ext-2.0.2.dist-info/METADATA
flake8_vcs_ext-2.0.2.dist-info/WHEEL
flake8_vcs_ext-2.0.2.dist-info/entry_points.txt
flake8_vcs_ext-2.0.2.dist-info/RECORD
