Metadata-Version: 2.1
Name: flake8-vcs-ext
Version: 2.0.2
Summary: Плагин flake8 с проверкой на дополнительные стандарты кода, принятые на проекте VCS
License: GPL-2.0 license
Author: Debianov
Author-email: regdeb@mail.ru
Requires-Python: >=3.10,<4.0
Classifier: Environment :: Console
Classifier: Framework :: Flake8
Classifier: Intended Audience :: Developers
Classifier: License :: OSI Approved :: GNU General Public License v2 (GPLv2)
Classifier: License :: Other/Proprietary License
Classifier: Programming Language :: Python
Classifier: Programming Language :: Python :: 3
Classifier: Programming Language :: Python :: 3.10
Classifier: Programming Language :: Python :: 3.11
Classifier: Topic :: Software Development :: Libraries :: Python Modules
Classifier: Topic :: Software Development :: Quality Assurance
Requires-Dist: flake8 (>=6.0.0,<7.0.0)
Requires-Dist: flake8-isort (>=6.0.0,<7.0.0)
Requires-Dist: flake8-pyproject (>=1.2.3,<2.0.0)
Requires-Dist: isort (>=5.12.0,<6.0.0)
Requires-Dist: mypy (>=1.4.1,<2.0.0)
Requires-Dist: pytest (>=7.4.0,<8.0.0)
Project-URL: Repository, https://github.com/GREEN-Corporation/vcs-style-flake8-extension
